cut_pursuit_py/__init__.py
cut_pursuit_py/_cut_pursuit.cpython-39-i386-linux-gnu.so
cut_pursuit_py-1.0.12.dist-info/METADATA
cut_pursuit_py-1.0.12.dist-info/WHEEL
cut_pursuit_py-1.0.12.dist-info/top_level.txt
cut_pursuit_py-1.0.12.dist-info/RECORD
cut_pursuit_py-1.0.12.dist-info/licenses/LICENSE
